[
  {
    "employer_name": "Salesforce",
    "job_title": "SMTS/LMTS Full Stack, Software Developer, BE Leaning (Service Cloud)",
    "job_city": "Bellevue",
    "job_state": "WA",
    "job_posted_at": "1h",
    "job_description": "• Build scalable, reliable, maintainable, high-performing web applications using Java-based technologies for the backend and modern JavaScript frameworks for the frontend that meet business requirements.\n• Collaborate with product managers, designers, and other stakeholders to define project requirements and deliverables.\n• Life at Salesforce Our Locations Our Locations North America Europe, Middle East, and Africa Asia Pacific Latin America Our Teams Our Teams Sales Technology & Product Customer Success Corporate Roles AI Research University University Overview Interns New Grads Advanced Degrees Associate Program Manager Talent Programs Talent Programs Overview Future Pathways India Return to Work Military Fellows 5+ years of professional software development experience in building distributed systems.\n• Proven hands-on development experience with Java, Spring Boot, and a passion for developing and delivering high-quality code.\n• Experience with Spring, gRPC, REST, and the HTTP protocol.\n• Experience with Agile development methodology.\n• Strong communication skills and the ability to collaborate effectively across teams.\n• Experience in developing and maintaining high-availability systems.",
    "job_apply_link": "https://careers.salesforce.com/en/jobs/jr321564/smtslmts-full-stack-software-developer-be-leaning-service-cloud/",
    "id": "salesforce-smts-lmts-full-stack-software-developer-be-leaning-service-cloud-bellevue"
  }
]